<?xml version = '1.0' encoding = 'UTF-8'?>
<FKIndexAssociation class="oracle.dbtools.crest.model.design.relational.FKIndexAssociation" directorySegmentName="seg_0" id="E1EC14EB-ED47-0C15-EBFC-465AE471B5D5" containerWithKeyObject="0551BCF0-D332-9594-4497-DC86EACFA099" localFKIndex="42123F27-D465-77C8-08FE-7DDADF10B78C" name="FK_LOAN_WAITING_TO_LOAN_DOC">
<sourceConnName>docker-SCOTT</sourceConnName>
<sourceObjSchema>SCOTT</sourceObjSchema>
<sourceObjName>FK_LOAN_WAITING_TO_LOAN_DOC</sourceObjName>
<createdBy>linakim</createdBy>
<createdTime>2020-06-07 12:48:57 UTC</createdTime>
<ownerDesignName>modeling</ownerDesignName>
<referredTableLongName>SCOTT.LOAN_WAITING</referredTableLongName>
<deleteRule>NO ACTION</deleteRule>
<referredTableID>B77BEB26-A133-ED69-3532-6E8FE9FE7C79</referredTableID>
<keyObject>D63793FD-45E9-CE39-0CAF-6986AA527229</keyObject>
<referredKeyID>D63793FD-45E9-CE39-0CAF-6986AA527229</referredKeyID>
<mandatory>true</mandatory>
<refColNames>APP_NO</refColNames>
<transferable>true</transferable>
<rely>false</rely>
<columnDependencyConstraintGenerateInDDL>true</columnDependencyConstraintGenerateInDDL>
</FKIndexAssociation>